README.txt
setup.py
bright/__init__.py
bright/_delete.py
bright/_exception.py
bright/_get.py
bright/_post.py
bright/_put.py
bright/christmastree.py
bright/delete.py
bright/fanyi.py
bright/ftime.py
bright/get.py
bright/kill.py
bright/post.py
bright/put.py
bright/req.py
bright.egg-info/PKG-INFO
bright.egg-info/SOURCES.txt
bright.egg-info/dependency_links.txt
bright.egg-info/requires.txt
bright.egg-info/top_level.txt