Metadata-Version: 1.0
Name: bright
Version: 0.0.17
Summary: bright tool
Home-page: https://github.com/brightlike/Christmastree/
Author: bright
Author-email: brightmail@vip.qq.com
License: MIT Licence
Keywords: tool,bright
Platform: any
